rds_cognito_pkg/__init__.py
rds_cognito_pkg/functions.py
rds_cognito_pkg/main.py
rds_cognito_pkg/models.py
rds_cognito_pkg/settings.py
rds_cognito_attributes-0.0.2.dist-info/LICENSE
rds_cognito_attributes-0.0.2.dist-info/METADATA
rds_cognito_attributes-0.0.2.dist-info/WHEEL
rds_cognito_attributes-0.0.2.dist-info/top_level.txt
rds_cognito_attributes-0.0.2.dist-info/RECORD
