Metadata-Version: 2.1
Name: rds-cognito-attributes
Version: 0.0.2
Summary: A small package which can be used to query user information from both AWS Cognito and AWS Aurora RDS.
Home-page: https://github.com/brandonrosenbloom/RDS_Cognito_attribute_alignment
Author: Brandon Rosenbloom
Author-email: brandonrosenbloom@gmail.com
License: UNKNOWN
Platform: UNKNOWN
Classifier: Programming Language :: Python :: 3
Classifier: License :: OSI Approved :: MIT License
Classifier: Operating System :: OS Independent
Requires-Python: >=3.6
